flaskstream2py/__init__.py
flaskstream2py-0.0.2.dist-info/LICENSE
flaskstream2py-0.0.2.dist-info/METADATA
flaskstream2py-0.0.2.dist-info/WHEEL
flaskstream2py-0.0.2.dist-info/top_level.txt
flaskstream2py-0.0.2.dist-info/RECORD
