Metadata-Version: 2.1
Name: flaskstream2py
Version: 0.0.2
Summary: stream2py interface to flask
Home-page: https://github.com/i2mint/flaskstream2py
Author: OtoSense
License: apache-2.0
Platform: any
